<templateSet group="typescript_angular">
  <template name="serv" value="private $NAME$: $CLASS$" description="private service parameter" toReformat="false" toShortenFQNames="true">
    <variable name="NAME" expression="" defaultValue="" alwaysStopAt="true" />
    <variable name="CLASS" expression="" defaultValue="" alwaysStopAt="true" />
    <context>
      <option name="TypeScript" value="true" />
    </context>
  </template>
  <template name="serb" value="public $NAME$: $CLASS$" description="public service parameter" toReformat="false" toShortenFQNames="true">
    <variable name="NAME" expression="" defaultValue="" alwaysStopAt="true" />
    <variable name="CLASS" expression="" defaultValue="" alwaysStopAt="true" />
    <context>
      <option name="TypeScript" value="true" />
    </context>
  </template>
  <template name="nav" value="this.router.navigate([$ROUTE$]);" description="router navigation" toReformat="false" toShortenFQNames="true">
    <variable name="ROUTE" expression="" defaultValue="" alwaysStopAt="true" />
    <context>
      <option name="TypeScript" value="true" />
    </context>
  </template>
  <template name="navr" value="this.router.navigate([$ROUTE$], { relativeTo: this.route });" description="relative router navigation" toReformat="false" toShortenFQNames="true">
    <variable name="ROUTE" expression="" defaultValue="" alwaysStopAt="true" />
    <context>
      <option name="TypeScript" value="true" />
    </context>
  </template>
  <template name="route" value="{&#10;  path: $PATH$,&#10;  component: $COMPONENT$&#10;}" description="component route definition" toReformat="false" toShortenFQNames="true">
    <variable name="PATH" expression="" defaultValue="" alwaysStopAt="true" />
    <variable name="COMPONENT" expression="" defaultValue="" alwaysStopAt="true" />
    <context>
      <option name="TypeScript" value="true" />
    </context>
  </template>
  <template name="router" value="{&#10;  path: '',&#10;  redirectTo: $PATH$,&#10;  pathMatch: 'full'&#10;}" description="redirect route definition" toReformat="false" toShortenFQNames="true">
    <variable name="PATH" expression="" defaultValue="" alwaysStopAt="true" />
    <context>
      <option name="TypeScript" value="true" />
    </context>
  </template>
</templateSet>